LICENSE
README.md
imslp/__init__.py
imslp/client.py
imslp/helpers/string_search.py
imslp/interfaces/__init__.py
imslp/interfaces/constants.py
imslp/interfaces/internal.py
imslp/interfaces/mw_api.py
imslp/interfaces/scraping.py
imslp-0.2.1.dist-info/LICENSE
imslp-0.2.1.dist-info/WHEEL
imslp-0.2.1.dist-info/METADATA
imslp-0.2.1.dist-info/RECORD
