Metadata-Version: 2.1
Name: imslp
Version: 0.2.1
Summary: The clean and modern way of accessing IMSLP data and scores programmatically.
Home-page: https://github.com/jlumbroso/imslp
License: LGPL-3.0-or-later
Keywords: IMSLP,IMSLP-scraper,IMSLP-scraping,sheet-music,music-data
Author: Jérémie Lumbroso
Author-email: lumbroso@cs.princeton.edu
Requires-Python: >=3.8,<4.0
Classifier: Development Status :: 3 - Alpha
Classifier: License :: OSI Approved :: GNU Lesser General Public License v3 or later (LGPLv3+)
Classifier: Programming Language :: Python :: 3
Classifier: Programming Language :: Python :: 3.8
Classifier: Programming Language :: Python :: 3.9
Classifier: Topic :: Artistic Software
Classifier: Topic :: Scientific/Engineering :: Information Analysis
Classifier: Topic :: Software Development :: Libraries :: Python Modules
Requires-Dist: bs4 (>=0.0.1,<0.0.2)
Requires-Dist: mwclient (>=0.10.1,<0.11.0)
Requires-Dist: requests (>=2.24.0,<3.0.0)
Project-URL: Repository, https://github.com/jlumbroso/imslp
